pydmclab/core/README.md
pydmclab/core/__init__.py
pydmclab/core/alloys.py
pydmclab/core/comp.py
pydmclab/core/defects.py
pydmclab/core/energies.py
pydmclab/core/hulls.py
pydmclab/core/mag.py
pydmclab/core/query.py
pydmclab/core/struc.py
pydmclab/data/.DS_Store
pydmclab/data/README.md
pydmclab/data/__init__.py
pydmclab/data/configs.py
pydmclab/data/features.py
pydmclab/data/plotting_configs.py
pydmclab/data/thermochem.py
pydmclab/data/data/221220_dmc-mus.json
pydmclab/data/data/230122_dmc-mus.json
pydmclab/data/data/230614_dmc-mus.json
pydmclab/data/data/231002_dmc-mus.json
pydmclab/data/data/_batch_vasp_analysis_configs.yaml
pydmclab/data/data/_hpc_configs.yaml
pydmclab/data/data/_launch_configs.yaml
pydmclab/data/data/_partition_configs.yaml
pydmclab/data/data/_slurm_configs.yaml
pydmclab/data/data/_sub_configs.yaml
pydmclab/data/data/_vasp_configs.yaml
pydmclab/data/data/atomic_electronegativities.json
pydmclab/data/data/atomic_masses.json
pydmclab/data/data/bartel2019_npj_reference-energies.csv
pydmclab/data/data/colors.json
pydmclab/data/data/elemental_gibbs_energies_T.json
pydmclab/data/data/gas_thermo_data_nist.json
pydmclab/data/data/mp2020_compatibility_dmus.json
pydmclab/data/data/mus_from_bartel2019_npj.json
pydmclab/data/data/mus_from_dmc_no_corrections.json
pydmclab/data/data/mus_from_mp_no_corrections.json
pydmclab/data/data/shannon_revised_effective_ionic_radii.json
pydmclab/data/data/ssub.dat
pydmclab/data/data/ssub.json
pydmclab/demos/demo_chgnet_md.py
pydmclab/demos/demo_comp.py
pydmclab/demos/demo_energies.py
pydmclab/demos/demo_hulls.py
pydmclab/demos/demo_launcher_template.py
pydmclab/demos/demo_mag.py
pydmclab/demos/demo_old_query.py
pydmclab/demos/demo_plot_dos.py
pydmclab/demos/demo_query.py
pydmclab/demos/demo_struc.py
pydmclab/demos/dev/demo_launch_defects.py
pydmclab/demos/dev/understanding_interface_rxns.py
pydmclab/demos/launches/defects/neutral_then_charged/charged/scripts/launcher.py
pydmclab-1.3.0.dist-info/LICENSE.txt
pydmclab-1.3.0.dist-info/METADATA
pydmclab-1.3.0.dist-info/WHEEL
pydmclab-1.3.0.dist-info/top_level.txt
pydmclab-1.3.0.dist-info/RECORD
